jb_reasoning_engine/__init__.py
jb_reasoning_engine/reasoning_engine_plugin.py
jb_reasoning_engine-0.1.1.dist-info/METADATA
jb_reasoning_engine-0.1.1.dist-info/WHEEL
jb_reasoning_engine-0.1.1.dist-info/RECORD
